{"assets":[{"id":"5","layers":[{"ind":4,"ty":4,"ks":{},"ip":0,"op":68.2,"st":0,"shapes":[{"ty":"rc","p":{"a":0,"k":[18.5,19]},"r":{"a":0,"k":0},"s":{"a":0,"k":[37,38]}},{"ty":"fl","c":{"a":0,"k":[0,0,0,0]},"o":{"a":0,"k":0}}]},{"ind":0,"ty":4,"ks":{"s":{"a":0,"k":[133.33,133.33]}},"ip":0,"op":68.2,"st":0,"shapes":[{"ty":"gr","it":[{"ty":"gr","it":[{"ty":"sh","ks":{"a":0,"k":{"c":true,"i":[[0,0],[0,0],[0,0],[0,0],[0,0],[0,0],[0,0],[0,0]],"o":[[0,0],[0,0],[0,0],[0,0],[0,0],[0,0],[0,0],[0,0]],"v":[[0.41,28.5],[11.23,0.35],[16.46,0.35],[27.2,28.5],[21.89,28.5],[19.28,21.1],[8.3,21.1],[5.77,28.5]]}}},{"ty":"sh","ks":{"a":0,"k":{"c":true,"i":[[0,0],[0,0],[0,0],[0.44,1.69],[0,0],[0.61,-1.77]],"o":[[0,0],[0,0],[-0.52,-1.49],[0,0],[-0.52,1.97],[0,0]],"v":[[9.79,16.88],[17.79,16.88],[15.42,10.08],[13.77,4.97],[13.73,4.97],[12.12,10.08]]}}},{"ty":"fl","c":{"a":0,"k":[0,0,0,1]},"o":{"a":0,"k":100}},{"ty":"tr","o":{"a":0,"k":100}}]},{"ty":"tr","o":{"a":0,"k":100}}]}]}]},{"id":"11","layers":[{"ind":10,"ty":4,"ks":{},"ip":0,"op":68.2,"st":0,"shapes":[{"ty":"rc","p":{"a":0,"k":[14.5,19]},"r":{"a":0,"k":0},"s":{"a":0,"k":[29,38]}},{"ty":"fl","c":{"a":0,"k":[0,0,0,0]},"o":{"a":0,"k":0}}]},{"ind":0,"ty":4,"ks":{"s":{"a":0,"k":[133.33,133.33]}},"ip":0,"op":68.2,"st":0,"shapes":[{"ty":"gr","it":[{"ty":"gr","it":[{"ty":"sh","ks":{"a":0,"k":{"c":true,"i":[[0,0],[0,0],[0,0],[0,-7.88],[5.27,0],[0,0],[0,0]],"o":[[0,0],[0,0],[5.19,0],[0,7.8],[0,0],[0,0],[0,0]],"v":[[0.02,28.5],[0.02,0.35],[10.03,0.35],[21.53,9.07],[9.99,17.72],[5.04,17.72],[5.04,28.5]]}}},{"ty":"sh","ks":{"a":0,"k":{"c":true,"i":[[0,0],[0,0],[0,4.43],[3.26,0],[0,0]],"o":[[0,0],[3.3,0],[0,-4.59],[0,0],[0,0]],"v":[[5.04,13.7],[9.91,13.7],[16.5,9.07],[9.95,4.41],[5.04,4.41]]}}},{"ty":"fl","c":{"a":0,"k":[0,0,0,1]},"o":{"a":0,"k":100}},{"ty":"tr","o":{"a":0,"k":100}}]},{"ty":"tr","o":{"a":0,"k":100}}]}]}]},{"id":"18","layers":[{"ind":17,"ty":4,"ks":{},"ip":0,"op":68.2,"st":0,"shapes":[{"ty":"rc","p":{"a":0,"k":[4,19]},"r":{"a":0,"k":0},"s":{"a":0,"k":[8,38]}},{"ty":"fl","c":{"a":0,"k":[0,0,0,0]},"o":{"a":0,"k":0}}]},{"ind":0,"ty":4,"ks":{"s":{"a":0,"k":[133.33,133.33]}},"ip":0,"op":68.2,"st":0,"shapes":[{"ty":"gr","it":[{"ty":"gr","it":[{"ty":"sh","ks":{"a":0,"k":{"c":true,"i":[[0,0],[0,0],[0,0],[0,0]],"o":[[0,0],[0,0],[0,0],[0,0]],"v":[[0.54,28.5],[0.54,8.39],[5.32,8.39],[5.32,28.5]]}}},{"ty":"sh","ks":{"a":0,"k":{"c":true,"i":[[0,0],[0,0],[0,0],[0,0]],"o":[[0,0],[0,0],[0,0],[0,0]],"v":[[0.58,5.25],[0.58,0.11],[5.32,0.11],[5.32,5.25]]}}},{"ty":"fl","c":{"a":0,"k":[0,0,0,1]},"o":{"a":0,"k":100}},{"ty":"tr","o":{"a":0,"k":100}}]},{"ty":"tr","o":{"a":0,"k":100}}]}]}]},{"id":"24","layers":[{"ind":23,"ty":4,"ks":{},"ip":0,"op":68.2,"st":0,"shapes":[{"ty":"rc","p":{"a":0,"k":[12.5,14]},"r":{"a":0,"k":0},"s":{"a":0,"k":[25,28]}},{"ty":"fl","c":{"a":0,"k":[0,0,0,0]},"o":{"a":0,"k":0}}]},{"ind":0,"ty":4,"ks":{"s":{"a":0,"k":[133.33,133.33]}},"ip":0,"op":68.2,"st":0,"shapes":[{"ty":"gr","it":[{"ty":"gr","it":[{"ty":"sh","ks":{"a":0,"k":{"c":true,"i":[[0,0],[0,0],[0,0],[0,0],[-2.89,0],[-1.37,-1.41],[0,-2.41],[0,0],[0,0],[0,0],[1.05,0.96],[1.16,0],[0,-4.87],[0,0]],"o":[[0,0],[0,0],[0,0],[1.01,-2.45],[2.61,0],[1.57,1.61],[0,0],[0,0],[0,0],[0,-1.85],[-0.89,-0.88],[-1.77,0],[0,0],[0,0]],"v":[[0.01,21],[0.01,0.89],[4.75,0.89],[4.75,3.95],[10.83,0.41],[16.46,2.46],[18.15,8.86],[18.15,21],[13.32,21],[13.32,9.21],[12.2,5.11],[9.18,4.15],[4.79,9.98],[4.79,21]]}}},{"ty":"fl","c":{"a":0,"k":[0,0,0,1]},"o":{"a":0,"k":100}},{"ty":"tr","o":{"a":0,"k":100}}]},{"ty":"tr","o":{"a":0,"k":100}}]}]}]},{"id":"30","layers":[{"ind":29,"ty":4,"ks":{},"ip":0,"op":68.2,"st":0,"shapes":[{"ty":"rc","p":{"a":0,"k":[13,19]},"r":{"a":0,"k":0},"s":{"a":0,"k":[26,38]}},{"ty":"fl","c":{"a":0,"k":[0,0,0,0]},"o":{"a":0,"k":0}}]},{"ind":0,"ty":4,"ks":{"s":{"a":0,"k":[133.33,133.33]}},"ip":0,"op":68.2,"st":0,"shapes":[{"ty":"gr","it":[{"ty":"gr","it":[{"ty":"gr","it":[{"ty":"sh","ks":{"a":0,"k":{"c":true,"i":[[0,0],[0,0],[0,0],[0,0],[-2.7,0],[-1.41,-1.53],[0,-2.5],[0,0],[0,0],[0,0],[1,0.96],[1.17,0],[0,-4.79],[0,0]],"o":[[0,0],[0,0],[0,0],[1.09,-2.33],[2.61,0],[1.53,1.65],[0,0],[0,0],[0,0],[0,-1.85],[-0.93,-0.92],[-1.73,0],[0,0],[0,0]],"v":[[0.68,28.5],[0.68,0.35],[5.42,0.35],[5.42,11.37],[11.41,7.91],[17.16,10.04],[18.81,16.36],[18.81,28.5],[13.99,28.5],[13.99,16.59],[12.9,12.65],[9.84,11.65],[5.46,17.32],[5.46,28.5]]}}},{"ty":"fl","c":{"a":0,"k":[0,0,0,1]},"o":{"a":0,"k":100}},{"ty":"tr","o":{"a":0,"k":100}}]},{"ty":"tr","o":{"a":0,"k":100}}]},{"ty":"tr","o":{"a":0,"k":100}}]}]}]},{"id":"36","layers":[{"ind":35,"ty":4,"ks":{},"ip":0,"op":68.2,"st":0,"shapes":[{"ty":"rc","p":{"a":0,"k":[14,14.5]},"r":{"a":0,"k":0},"s":{"a":0,"k":[28,29]}},{"ty":"fl","c":{"a":0,"k":[0,0,0,0]},"o":{"a":0,"k":0}}]},{"ind":0,"ty":4,"ks":{"s":{"a":0,"k":[133.33,133.33]}},"ip":0,"op":68.2,"st":0,"shapes":[{"ty":"gr","it":[{"ty":"gr","it":[{"ty":"sh","ks":{"a":0,"k":{"c":true,"i":[[0,0],[0,6.55],[-6.39,0],[0,-6.07],[6.2,0]],"o":[[-6.43,0],[0,-6.11],[6.32,0],[0,6.31],[0,0]],"v":[[10.51,21.48],[0.21,10.95],[10.51,0.41],[20.73,10.95],[10.51,21.48]]}}},{"ty":"sh","ks":{"a":0,"k":{"c":true,"i":[[0,0],[-1.05,-1.13],[-1.69,0],[-0.8,0.96],[0,2.57],[0.96,1.16],[1.69,0],[0.8,-0.93],[0,-2.66]],"o":[[0,2.66],[0.8,0.93],[1.69,0],[0.96,-1.16],[0,-2.57],[-0.8,-0.96],[-1.65,0],[-1.05,1.13],[0,0]],"v":[[5.32,10.95],[6.81,16.62],[10.51,17.98],[14.25,16.54],[15.62,10.95],[14.21,5.36],[10.51,3.91],[6.81,5.27],[5.32,10.95]]}}},{"ty":"fl","c":{"a":0,"k":[0,0,0,1]},"o":{"a":0,"k":100}},{"ty":"tr","o":{"a":0,"k":100}}]},{"ty":"tr","o":{"a":0,"k":100}}]}]}]},{"id":"39","layers":[{"ind":20,"ty":0,"parent":16,"ks":{},"w":8,"h":38,"ip":0,"op":68.2,"st":0,"refId":"18"},{"ind":16,"ty":3,"parent":15,"ks":{"s":{"a":0,"k":[219.91,219.6]}},"ip":0,"op":68.2,"st":0},{"ind":15,"ty":3,"parent":14,"ks":{"p":{"a":0,"k":[-1.577,-0.309]}},"ip":0,"op":68.2,"st":0},{"ind":26,"ty":0,"parent":22,"ks":{},"w":25,"h":28,"ip":0,"op":68.2,"st":0,"refId":"24"},{"ind":22,"ty":3,"parent":21,"ks":{"s":{"a":0,"k":[219.91,219.6]}},"ip":0,"op":68.2,"st":0},{"ind":21,"ty":3,"parent":14,"ks":{"p":{"a":0,"k":[27.011,21.651]}},"ip":0,"op":68.2,"st":0},{"ind":32,"ty":0,"parent":28,"ks":{},"w":26,"h":38,"ip":0,"op":68.2,"st":0,"refId":"30"},{"ind":28,"ty":3,"parent":27,"ks":{"s":{"a":0,"k":[219.91,219.6]}},"ip":0,"op":68.2,"st":0},{"ind":27,"ty":3,"parent":14,"ks":{"p":{"a":0,"k":[90.786,-0.309]}},"ip":0,"op":68.2,"st":0},{"ind":38,"ty":0,"parent":34,"ks":{},"w":28,"h":29,"ip":0,"op":68.2,"st":0,"refId":"36"},{"ind":34,"ty":3,"parent":33,"ks":{"s":{"a":0,"k":[219.91,219.6]}},"ip":0,"op":68.2,"st":0},{"ind":33,"ty":3,"parent":14,"ks":{"p":{"a":0,"k":[154.561,21.651]}},"ip":0,"op":68.2,"st":0},{"ind":14,"ty":3,"ks":{"p":{"a":0,"k":[2,1]}},"ip":0,"op":68.2,"st":0}]},{"id":"46","layers":[{"ind":45,"ty":4,"ks":{},"ip":0,"op":68.2,"st":0,"shapes":[{"ty":"rc","p":{"a":0,"k":[4,19]},"r":{"a":0,"k":0},"s":{"a":0,"k":[8,38]}},{"ty":"fl","c":{"a":0,"k":[0,0,0,0]},"o":{"a":0,"k":0}}]},{"ind":0,"ty":4,"ks":{"s":{"a":0,"k":[133.33,133.33]}},"ip":0,"op":68.2,"st":0,"shapes":[{"ty":"gr","it":[{"ty":"gr","it":[{"ty":"sh","ks":{"a":0,"k":{"c":true,"i":[[0,0],[0,0],[0,0],[0,0]],"o":[[0,0],[0,0],[0,0],[0,0]],"v":[[0.54,28.5],[0.54,0.35],[5.32,0.35],[5.32,28.5]]}}},{"ty":"fl","c":{"a":0,"k":[0,0,0,1]},"o":{"a":0,"k":100}},{"ty":"tr","o":{"a":0,"k":100}}]},{"ty":"tr","o":{"a":0,"k":100}}]}]}]},{"id":"52","layers":[{"ind":51,"ty":4,"ks":{},"ip":0,"op":68.2,"st":0,"shapes":[{"ty":"rc","p":{"a":0,"k":[13.5,19.5]},"r":{"a":0,"k":0},"s":{"a":0,"k":[27,39]}},{"ty":"fl","c":{"a":0,"k":[0,0,0,0]},"o":{"a":0,"k":0}}]},{"ind":0,"ty":4,"ks":{"s":{"a":0,"k":[133.33,133.33]}},"ip":0,"op":68.2,"st":0,"shapes":[{"ty":"gr","it":[{"ty":"gr","it":[{"ty":"sh","ks":{"a":0,"k":{"c":true,"i":[[0,0],[1.17,1.93],[0,0],[0,0],[0,0],[0,0],[0,0],[-2.57,0],[0,-6.36],[5.35,0]],"o":[[-2.62,0],[0,0],[0,0],[0,0],[0,0],[0,0],[1.33,-1.93],[5.31,0],[0,6.52],[0,0]],"v":[[10.79,28.98],[4.79,25.73],[4.79,28.5],[0.01,28.5],[0.01,0.35],[4.79,0.35],[4.79,10.88],[10.91,7.87],[19.88,18.45],[10.79,28.98]]}}},{"ty":"sh","ks":{"a":0,"k":{"c":true,"i":[[0,0],[-3.34,0],[-0.8,0.85],[0,2.66],[3.78,0],[0.76,-0.96],[0,-2.29]],"o":[[0,4.55],[1.57,0],[1.05,-1.16],[0,-4.63],[-1.65,0],[-1.01,1.29],[0,0]],"v":[[4.68,18.48],[9.66,25.48],[13.2,24.2],[14.69,18.45],[9.62,11.41],[6.04,12.93],[4.68,18.48]]}}},{"ty":"fl","c":{"a":0,"k":[0,0,0,1]},"o":{"a":0,"k":100}},{"ty":"tr","o":{"a":0,"k":100}}]},{"ty":"tr","o":{"a":0,"k":100}}]}]}]},{"id":"58","layers":[{"ind":57,"ty":4,"ks":{},"ip":0,"op":68.2,"st":0,"shapes":[{"ty":"rc","p":{"a":0,"k":[12.5,14]},"r":{"a":0,"k":0},"s":{"a":0,"k":[25,28]}},{"ty":"fl","c":{"a":0,"k":[0,0,0,0]},"o":{"a":0,"k":0}}]},{"ind":0,"ty":4,"ks":{"s":{"a":0,"k":[133.33,133.33]}},"ip":0,"op":68.2,"st":0,"shapes":[{"ty":"gr","it":[{"ty":"gr","it":[{"ty":"sh","ks":{"a":0,"k":{"c":true,"i":[[0,0],[1.45,1.53],[0,2.45],[0,0],[0,0],[0,0],[-0.96,-1],[-1.17,0],[0,4.79],[0,0],[0,0],[0,0],[0,0],[0,0],[2.78,0]],"o":[[-2.57,0],[-1.57,-1.65],[0,0],[0,0],[0,0],[0,1.85],[0.96,0.96],[1.89,0],[0,0],[0,0],[0,0],[0,0],[0,0],[-1.09,2.21],[0,0]],"v":[[8.07,20.73],[2.28,18.52],[0.55,11.93],[0.55,0.14],[5.42,0.14],[5.42,11.68],[6.42,15.95],[9.6,16.99],[13.95,11.24],[13.95,0.14],[18.65,0.14],[18.65,20.25],[13.98,20.25],[13.98,17.31],[8.07,20.73]]}}},{"ty":"fl","c":{"a":0,"k":[0,0,0,1]},"o":{"a":0,"k":100}},{"ty":"tr","o":{"a":0,"k":100}}]},{"ty":"tr","o":{"a":0,"k":100}}]}]}]},{"id":"64","layers":[{"ind":63,"ty":4,"ks":{},"ip":0,"op":68.2,"st":0,"shapes":[{"ty":"rc","p":{"a":0,"k":[13.5,19.5]},"r":{"a":0,"k":0},"s":{"a":0,"k":[27,39]}},{"ty":"fl","c":{"a":0,"k":[0,0,0,0]},"o":{"a":0,"k":0}}]},{"ind":0,"ty":4,"ks":{"s":{"a":0,"k":[133.33,133.33]}},"ip":0,"op":68.2,"st":0,"shapes":[{"ty":"gr","it":[{"ty":"gr","it":[{"ty":"sh","ks":{"a":0,"k":{"c":true,"i":[[0,0],[0,0],[2.7,0],[0,6.36],[-5.19,0],[-1.41,-2.13],[0,0],[0,0],[0,0]],"o":[[0,0],[-1.45,2.01],[-5.35,0],[0,-6.55],[2.61,0],[0,0],[0,0],[0,0],[0,0]],"v":[[15.38,29.04],[15.38,18.51],[9.22,21.48],[0.25,10.95],[9.26,0.37],[15.38,3.66],[15.38,0.89],[20.12,0.89],[20.12,29.04]]}}},{"ty":"sh","ks":{"a":0,"k":{"c":true,"i":[[0,0],[-3.82,0],[-0.77,0.8],[0,2.41],[3.34,0],[0.8,-0.93],[0,-2.57]],"o":[[0,4.66],[1.45,0],[1.16,-1.25],[0,-4.46],[-1.69,0],[-1,1.17],[0,0]],"v":[[5.44,10.91],[10.59,17.94],[13.93,16.66],[15.5,10.91],[10.51,3.91],[6.85,5.27],[5.44,10.91]]}}},{"ty":"fl","c":{"a":0,"k":[0,0,0,1]},"o":{"a":0,"k":100}},{"ty":"tr","o":{"a":0,"k":100}}]},{"ty":"tr","o":{"a":0,"k":100}}]}]}]},{"id":"70","layers":[{"ind":69,"ty":4,"ks":{},"ip":0,"op":68.2,"st":0,"shapes":[{"ty":"rc","p":{"a":0,"k":[12.5,14]},"r":{"a":0,"k":0},"s":{"a":0,"k":[25,28]}},{"ty":"fl","c":{"a":0,"k":[0,0,0,0]},"o":{"a":0,"k":0}}]},{"ind":0,"ty":4,"ks":{"s":{"a":0,"k":[133.33,133.33]}},"ip":0,"op":68.2,"st":0,"shapes":[{"ty":"gr","it":[{"ty":"gr","it":[{"ty":"sh","ks":{"a":0,"k":{"c":true,"i":[[0,0],[1.45,1.53],[0,2.45],[0,0],[0,0],[0,0],[-0.96,-1],[-1.16,0],[0,4.79],[0,0],[0,0],[0,0],[0,0],[0,0],[2.77,0]],"o":[[-2.57,0],[-1.57,-1.65],[0,0],[0,0],[0,0],[0,1.85],[0.96,0.96],[1.89,0],[0,0],[0,0],[0,0],[0,0],[0,0],[-1.09,2.21],[0,0]],"v":[[7.94,20.73],[2.15,18.52],[0.42,11.93],[0.42,0.14],[5.29,0.14],[5.29,11.68],[6.29,15.95],[9.47,16.99],[13.81,11.24],[13.81,0.14],[18.52,0.14],[18.52,20.25],[13.85,20.25],[13.85,17.31],[7.94,20.73]]}}},{"ty":"fl","c":{"a":0,"k":[0,0,0,1]},"o":{"a":0,"k":100}},{"ty":"tr","o":{"a":0,"k":100}}]},{"ty":"tr","o":{"a":0,"k":100}}]}]}]},{"id":"76","layers":[{"ind":75,"ty":4,"ks":{},"ip":0,"op":68.2,"st":0,"shapes":[{"ty":"rc","p":{"a":0,"k":[13.5,14.5]},"r":{"a":0,"k":0},"s":{"a":0,"k":[27,29]}},{"ty":"fl","c":{"a":0,"k":[0,0,0,0]},"o":{"a":0,"k":0}}]},{"ind":0,"ty":4,"ks":{"s":{"a":0,"k":[133.33,133.33]}},"ip":0,"op":68.2,"st":0,"shapes":[{"ty":"gr","it":[{"ty":"gr","it":[{"ty":"gr","it":[{"ty":"sh","ks":{"a":0,"k":{"c":true,"i":[[0,0],[1.73,1.77],[0,3.26],[-1.81,1.93],[-3.06,0],[-1.69,-2.13],[0.12,-3.46],[0,0],[-3.34,0],[-0.45,2.45],[0,0],[5.15,0]],"o":[[-3.14,0],[-1.85,-1.89],[0,-3.1],[1.77,-1.85],[3.18,0],[1.61,2.01],[0,0],[0.08,3.74],[2.93,0],[0,0],[-1.05,4.63],[0,0]],"v":[[10.1,21.48],[2.82,18.71],[0.12,10.91],[2.82,3.22],[10.06,0.41],[17.62,3.75],[19.91,12.27],[4.95,12.27],[10.06,17.9],[14.96,14.2],[19.59,14.57],[10.1,21.48]]}}},{"ty":"sh","ks":{"a":0,"k":{"c":true,"i":[[0,0],[0,0],[0.68,0.85],[1.77,0],[0.8,-1.12],[0.08,-0.96]],"o":[[0,0],[-0.08,-1.13],[-0.88,-1.09],[-1.89,0],[-0.64,0.88],[0,0]],"v":[[4.99,8.69],[15.04,8.69],[13.92,5.55],[10.06,3.99],[6,5.76],[4.99,8.69]]}}},{"ty":"fl","c":{"a":0,"k":[0,0,0,1]},"o":{"a":0,"k":100}},{"ty":"tr","o":{"a":0,"k":100}}]},{"ty":"tr","o":{"a":0,"k":100}}]},{"ty":"tr","o":{"a":0,"k":100}}]}]}]},{"id":"82","layers":[{"ind":81,"ty":4,"ks":{},"ip":0,"op":68.2,"st":0,"shapes":[{"ty":"rc","p":{"a":0,"k":[9,14]},"r":{"a":0,"k":0},"s":{"a":0,"k":[18,28]}},{"ty":"fl","c":{"a":0,"k":[0,0,0,0]},"o":{"a":0,"k":0}}]},{"ind":0,"ty":4,"ks":{"s":{"a":0,"k":[133.33,133.33]}},"ip":0,"op":68.2,"st":0,"shapes":[{"ty":"gr","it":[{"ty":"gr","it":[{"ty":"sh","ks":{"a":0,"k":{"c":true,"i":[[0,0],[0,0],[0,0],[0,0],[-3.26,0.24],[-0.32,0],[0,0],[0.36,0],[0,-5.55],[0,0]],"o":[[0,0],[0,0],[0,0],[0.64,-2.09],[0.32,-0.04],[0,0],[-0.28,-0.04],[-3.78,0],[0,0],[0,0]],"v":[[0.7,21],[0.7,0.89],[5.44,0.89],[5.44,4.51],[11.35,0.45],[12.76,0.41],[12.64,4.75],[11.63,4.71],[5.48,11.79],[5.48,21]]}}},{"ty":"fl","c":{"a":0,"k":[0,0,0,1]},"o":{"a":0,"k":100}},{"ty":"tr","o":{"a":0,"k":100}}]},{"ty":"tr","o":{"a":0,"k":100}}]}]}]},{"id":"88","layers":[{"ind":87,"ty":4,"ks":{},"ip":0,"op":68.2,"st":0,"shapes":[{"ty":"rc","p":{"a":0,"k":[14,19.5]},"r":{"a":0,"k":0},"s":{"a":0,"k":[28,39]}},{"ty":"fl","c":{"a":0,"k":[0,0,0,0]},"o":{"a":0,"k":0}}]},{"ind":0,"ty":4,"ks":{"s":{"a":0,"k":[133.33,133.33]}},"ip":0,"op":68.2,"st":0,"shapes":[{"ty":"gr","it":[{"ty":"gr","it":[{"ty":"sh","ks":{"a":0,"k":{"c":true,"i":[[0,0],[0,0],[2.7,0],[0,6.36],[-5.19,0],[-1.41,-2.13],[0,0],[0,0],[0,0]],"o":[[0,0],[-1.45,2.01],[-5.35,0],[0,-6.55],[2.61,0],[0,0],[0,0],[0,0],[0,0]],"v":[[15.8,29.04],[15.8,18.51],[9.64,21.48],[0.68,10.95],[9.68,0.37],[15.8,3.66],[15.8,0.89],[20.54,0.89],[20.54,29.04]]}}},{"ty":"sh","ks":{"a":0,"k":{"c":true,"i":[[0,0],[-3.82,0],[-0.76,0.8],[0,2.41],[3.34,0],[0.8,-0.93],[0,-2.57]],"o":[[0,4.66],[1.45,0],[1.17,-1.25],[0,-4.46],[-1.69,0],[-1,1.17],[0,0]],"v":[[5.86,10.91],[11.01,17.94],[14.35,16.66],[15.92,10.91],[10.93,3.91],[7.27,5.27],[5.86,10.91]]}}},{"ty":"fl","c":{"a":0,"k":[0,0,0,1]},"o":{"a":0,"k":100}},{"ty":"tr","o":{"a":0,"k":100}}]},{"ty":"tr","o":{"a":0,"k":100}}]}]}]},{"id":"94","layers":[{"ind":93,"ty":4,"ks":{},"ip":0,"op":68.2,"st":0,"shapes":[{"ty":"rc","p":{"a":0,"k":[12.5,14]},"r":{"a":0,"k":0},"s":{"a":0,"k":[25,28]}},{"ty":"fl","c":{"a":0,"k":[0,0,0,0]},"o":{"a":0,"k":0}}]},{"ind":0,"ty":4,"ks":{"s":{"a":0,"k":[133.33,133.33]}},"ip":0,"op":68.2,"st":0,"shapes":[{"ty":"gr","it":[{"ty":"gr","it":[{"ty":"sh","ks":{"a":0,"k":{"c":true,"i":[[0,0],[1.45,1.53],[0,2.45],[0,0],[0,0],[0,0],[-0.96,-1],[-1.17,0],[0,4.79],[0,0],[0,0],[0,0],[0,0],[0,0],[2.77,0]],"o":[[-2.57,0],[-1.57,-1.65],[0,0],[0,0],[0,0],[0,1.85],[0.96,0.96],[1.89,0],[0,0],[0,0],[0,0],[0,0],[0,0],[-1.09,2.21],[0,0]],"v":[[7.61,20.73],[1.82,18.52],[0.09,11.93],[0.09,0.14],[4.96,0.14],[4.96,11.68],[5.96,15.95],[9.14,16.99],[13.48,11.24],[13.48,0.14],[18.19,0.14],[18.19,20.25],[13.52,20.25],[13.52,17.31],[7.61,20.73]]}}},{"ty":"fl","c":{"a":0,"k":[0,0,0,1]},"o":{"a":0,"k":100}},{"ty":"tr","o":{"a":0,"k":100}}]},{"ty":"tr","o":{"a":0,"k":100}}]}]}]},{"id":"100","layers":[{"ind":99,"ty":4,"ks":{},"ip":0,"op":68.2,"st":0,"shapes":[{"ty":"rc","p":{"a":0,"k":[14,14.5]},"r":{"a":0,"k":0},"s":{"a":0,"k":[28,29]}},{"ty":"fl","c":{"a":0,"k":[0,0,0,0]},"o":{"a":0,"k":0}}]},{"ind":0,"ty":4,"ks":{"s":{"a":0,"k":[133.33,133.33]}},"ip":0,"op":68.2,"st":0,"shapes":[{"ty":"gr","it":[{"ty":"gr","it":[{"ty":"sh","ks":{"a":0,"k":{"c":true,"i":[[0,0],[1.73,1.77],[0,3.26],[-1.81,1.93],[-3.06,0],[-1.69,-2.13],[0.12,-3.46],[0,0],[-3.34,0],[-0.45,2.45],[0,0],[5.15,0]],"o":[[-3.14,0],[-1.85,-1.89],[0,-3.1],[1.77,-1.85],[3.18,0],[1.61,2.01],[0,0],[0.08,3.74],[2.93,0],[0,0],[-1.05,4.63],[0,0]],"v":[[10.52,21.48],[3.24,18.71],[0.54,10.91],[3.24,3.22],[10.48,0.41],[18.04,3.75],[20.33,12.27],[5.37,12.27],[10.48,17.9],[15.39,14.2],[20.01,14.57],[10.52,21.48]]}}},{"ty":"sh","ks":{"a":0,"k":{"c":true,"i":[[0,0],[0,0],[0.68,0.85],[1.77,0],[0.8,-1.12],[0.08,-0.96]],"o":[[0,0],[-0.08,-1.13],[-0.88,-1.09],[-1.89,0],[-0.64,0.88],[0,0]],"v":[[5.41,8.69],[15.46,8.69],[14.34,5.55],[10.48,3.99],[6.42,5.76],[5.41,8.69]]}}},{"ty":"fl","c":{"a":0,"k":[0,0,0,1]},"o":{"a":0,"k":100}},{"ty":"tr","o":{"a":0,"k":100}}]},{"ty":"tr","o":{"a":0,"k":100}}]}]}]},{"id":"103","layers":[{"ind":48,"ty":0,"parent":44,"ks":{},"w":8,"h":38,"ip":0,"op":68.2,"st":0,"refId":"46"},{"ind":44,"ty":3,"parent":43,"ks":{"s":{"a":0,"k":[219.91,219.6]}},"ip":0,"op":68.2,"st":0},{"ind":43,"ty":3,"parent":42,"ks":{"p":{"a":0,"k":[-1.577,-1.015]}},"ip":0,"op":68.2,"st":0},{"ind":54,"ty":0,"parent":50,"ks":{},"w":27,"h":39,"ip":0,"op":68.2,"st":0,"refId":"52"},{"ind":50,"ty":3,"parent":49,"ks":{"s":{"a":0,"k":[219.91,219.6]}},"ip":0,"op":68.2,"st":0},{"ind":49,"ty":3,"parent":42,"ks":{"p":{"a":0,"k":[27.011,-1.015]}},"ip":0,"op":68.2,"st":0},{"ind":60,"ty":0,"parent":56,"ks":{},"w":25,"h":28,"ip":0,"op":68.2,"st":0,"refId":"58"},{"ind":56,"ty":3,"parent":55,"ks":{"s":{"a":0,"k":[219.91,219.6]}},"ip":0,"op":68.2,"st":0},{"ind":55,"ty":3,"parent":42,"ks":{"p":{"a":0,"k":[92.985,23.141]}},"ip":0,"op":68.2,"st":0},{"ind":66,"ty":0,"parent":62,"ks":{},"w":27,"h":39,"ip":0,"op":68.2,"st":0,"refId":"64"},{"ind":62,"ty":3,"parent":61,"ks":{"s":{"a":0,"k":[219.91,219.6]}},"ip":0,"op":68.2,"st":0},{"ind":61,"ty":3,"parent":42,"ks":{"p":{"a":0,"k":[156.76,20.945]}},"ip":0,"op":68.2,"st":0},{"ind":72,"ty":0,"parent":68,"ks":{},"w":25,"h":28,"ip":0,"op":68.2,"st":0,"refId":"70"},{"ind":68,"ty":3,"parent":67,"ks":{"s":{"a":0,"k":[219.91,219.6]}},"ip":0,"op":68.2,"st":0},{"ind":67,"ty":3,"parent":42,"ks":{"p":{"a":0,"k":[227.132,23.141]}},"ip":0,"op":68.2,"st":0},{"ind":78,"ty":0,"parent":74,"ks":{},"w":27,"h":29,"ip":0,"op":68.2,"st":0,"refId":"76"},{"ind":74,"ty":3,"parent":73,"ks":{"s":{"a":0,"k":[219.91,219.6]}},"ip":0,"op":68.2,"st":0},{"ind":73,"ty":3,"parent":42,"ks":{"p":{"a":0,"k":[290.906,20.945]}},"ip":0,"op":68.2,"st":0},{"ind":84,"ty":0,"parent":80,"ks":{},"w":18,"h":28,"ip":0,"op":68.2,"st":0,"refId":"82"},{"ind":80,"ty":3,"parent":79,"ks":{"s":{"a":0,"k":[219.91,219.6]}},"ip":0,"op":68.2,"st":0},{"ind":79,"ty":3,"parent":42,"ks":{"p":{"a":0,"k":[356.88,20.945]}},"ip":0,"op":68.2,"st":0},{"ind":90,"ty":0,"parent":86,"ks":{},"w":28,"h":39,"ip":0,"op":68.2,"st":0,"refId":"88"},{"ind":86,"ty":3,"parent":85,"ks":{"s":{"a":0,"k":[219.91,219.6]}},"ip":0,"op":68.2,"st":0},{"ind":85,"ty":3,"parent":42,"ks":{"p":{"a":0,"k":[394.265,20.945]}},"ip":0,"op":68.2,"st":0},{"ind":96,"ty":0,"parent":92,"ks":{},"w":25,"h":28,"ip":0,"op":68.2,"st":0,"refId":"94"},{"ind":92,"ty":3,"parent":91,"ks":{"s":{"a":0,"k":[219.91,219.6]}},"ip":0,"op":68.2,"st":0},{"ind":91,"ty":3,"parent":42,"ks":{"p":{"a":0,"k":[466.836,23.141]}},"ip":0,"op":68.2,"st":0},{"ind":102,"ty":0,"parent":98,"ks":{},"w":28,"h":29,"ip":0,"op":68.2,"st":0,"refId":"100"},{"ind":98,"ty":3,"parent":97,"ks":{"s":{"a":0,"k":[219.91,219.6]}},"ip":0,"op":68.2,"st":0},{"ind":97,"ty":3,"parent":42,"ks":{"p":{"a":0,"k":[528.412,20.945]}},"ip":0,"op":68.2,"st":0},{"ind":42,"ty":3,"ks":{"p":{"a":0,"k":[2,2]}},"ip":0,"op":68.2,"st":0}]},{"id":"110","layers":[{"ind":109,"ty":4,"ks":{},"ip":0,"op":68.2,"st":0,"shapes":[{"ty":"rc","p":{"a":0,"k":[12.5,14]},"r":{"a":0,"k":0},"s":{"a":0,"k":[25,28]}},{"ty":"fl","c":{"a":0,"k":[0,0,0,0]},"o":{"a":0,"k":0}}]},{"ind":0,"ty":4,"ks":{"s":{"a":0,"k":[133.33,133.33]}},"ip":0,"op":68.2,"st":0,"shapes":[{"ty":"gr","it":[{"ty":"gr","it":[{"ty":"sh","ks":{"a":0,"k":{"c":true,"i":[[0,0],[0.74,1.2],[2.82,0],[0,-4.39],[-5.23,0],[-0.97,1.3],[-0.05,-0.18],[4.16,0],[0,5.6],[-6.06,0],[-1.06,-1.11],[0.6,-1.2],[0.46,0.6],[-0.05,0.09]],"o":[[0.42,-0.93],[-0.97,-1.57],[-5.14,0],[-0.05,5.46],[3.75,0],[0.19,0],[-1.57,2.18],[-6.06,0],[0,-5.92],[3.38,0],[1.48,1.57],[-0.6,1.2],[-0.05,-0.05],[0,0]],"v":[[15.45,7.03],[15.36,3.42],[9.76,0.79],[1.85,10.13],[10.32,20.07],[17.67,15.96],[18.18,16.33],[9.8,21],[0,11.1],[10.27,0],[16.79,2.59],[18.13,6.89],[15.5,7.21],[15.45,7.03]]}}},{"ty":"fl","c":{"a":0,"k":[0,0,0,1]},"o":{"a":0,"k":100}},{"ty":"tr","o":{"a":0,"k":100}}]},{"ty":"tr","o":{"a":0,"k":100}}]}]}]},{"id":"116","layers":[{"ind":115,"ty":4,"ks":{},"ip":0,"op":68.2,"st":0,"shapes":[{"ty":"rc","p":{"a":0,"k":[14,14]},"r":{"a":0,"k":0},"s":{"a":0,"k":[28,28]}},{"ty":"fl","c":{"a":0,"k":[0,0,0,0]},"o":{"a":0,"k":0}}]},{"ind":0,"ty":4,"ks":{"s":{"a":0,"k":[133.33,133.33]}},"ip":0,"op":68.2,"st":0,"shapes":[{"ty":"gr","it":[{"ty":"gr","it":[{"ty":"sh","ks":{"a":0,"k":{"c":true,"i":[[0,0],[0,-5.96],[6.94,0],[0,4.9],[-5.92,0]],"o":[[5,0],[0,5.27],[-6.2,0],[0,-5.96],[0,0]],"v":[[11.07,0],[20.97,9.9],[10.38,21],[0.29,11.05],[11.07,0]]}}},{"ty":"sh","ks":{"a":0,"k":{"c":true,"i":[[0,0],[3.93,0],[0,-5.78],[-5,0],[0,4.9]],"o":[[0,-6.8],[-4.21,0],[0,5.37],[4.9,0],[0,0]],"v":[[19.02,11.05],[10.47,0.79],[2.23,10.36],[10.98,20.21],[19.02,11.05]]}}},{"ty":"fl","c":{"a":0,"k":[0,0,0,1]},"o":{"a":0,"k":100}},{"ty":"tr","o":{"a":0,"k":100}}]},{"ty":"tr","o":{"a":0,"k":100}}]}]}]},{"id":"122","layers":[{"ind":121,"ty":4,"ks":{},"ip":0,"op":68.2,"st":0,"shapes":[{"ty":"rc","p":{"a":0,"k":[3.5,3.5]},"r":{"a":0,"k":0},"s":{"a":0,"k":[7,7]}},{"ty":"fl","c":{"a":0,"k":[0,0,0,0]},"o":{"a":0,"k":0}}]},{"ind":0,"ty":4,"ks":{"s":{"a":0,"k":[133.33,133.33]}},"ip":0,"op":68.2,"st":0,"shapes":[{"ty":"gr","it":[{"ty":"gr","it":[{"ty":"gr","it":[{"ty":"sh","ks":{"a":0,"k":{"c":true,"i":[[0,0],[-1.25,0],[0,-1.25],[1.25,0],[0,1.25]],"o":[[0,-1.25],[1.25,0],[0,1.25],[-1.25,0],[0,0]],"v":[[0.46,2.98],[2.73,0.72],[5,2.98],[2.73,5.25],[0.46,2.98]]}}},{"ty":"fl","c":{"a":0,"k":[0,0,0,1]},"o":{"a":0,"k":100}},{"ty":"tr","o":{"a":0,"k":100}}]},{"ty":"tr","o":{"a":0,"k":100}}]},{"ty":"tr","o":{"a":0,"k":100}}]}]}]}],"fr":60,"h":121,"ip":0,"layers":[{"ind":7,"ty":0,"parent":3,"ks":{},"w":37,"h":38,"ip":0,"op":68.2,"st":0,"refId":"5"},{"ind":3,"ty":3,"parent":2,"ks":{"s":{"a":0,"k":[219.91,219.6]}},"ip":0,"op":68.2,"st":0},{"ind":2,"ty":3,"parent":1,"ks":{"p":{"a":0,"k":[4,5]}},"ip":0,"op":68.2,"st":0},{"ind":13,"ty":0,"parent":9,"ks":{},"w":29,"h":38,"ip":0,"op":68.2,"st":0,"refId":"11"},{"ind":9,"ty":3,"parent":8,"ks":{"s":{"a":0,"k":[219.91,219.6]}},"ip":0,"op":68.2,"st":0},{"ind":8,"ty":3,"parent":1,"ks":{"p":{"a":1,"k":[{"t":0,"s":[712.119,5],"i":{"x":[0.368,1],"y":[0.671,1]},"o":{"x":[0.758,0],"y":[0,0]}},{"t":24,"s":[182.448,5],"i":{"x":[0.662,1],"y":[0.834,1]},"o":{"x":[0.297,0],"y":[0.535,0]}},{"t":36,"s":[106.004,5],"i":{"x":[0.7,1],"y":[0.825,1]},"o":{"x":[0.357,0],"y":[0.522,0]}},{"t":42,"s":[93.128,5],"i":{"x":[1,1],"y":[1,1]},"o":{"x":[0,0],"y":[0,0]}},{"t":45,"s":[90.55,5],"i":{"x":[1,1],"y":[1,1]},"o":{"x":[0,0],"y":[0,0]}},{"t":48,"s":[90.119,5],"i":{"x":[1,1],"y":[1,1]},"o":{"x":[0,0],"y":[0,0]}},{"t":67.2,"s":[90.119,5],"h":1}]}},"ip":0,"op":68.2,"st":0},{"ind":41,"ty":0,"parent":1,"ks":{"a":{"a":0,"k":[2,1]},"o":{"a":1,"k":[{"t":0,"s":[100],"h":1},{"t":2.4,"s":[100],"i":{"x":1,"y":1},"o":{"x":0,"y":0}},{"t":12,"s":[0],"h":1},{"t":67.2,"s":[0],"h":1}]},"p":{"a":1,"k":[{"t":0,"s":[784.068,5.309],"i":{"x":[1,1],"y":[1,1]},"o":{"x":[0,0],"y":[0,0]}},{"t":2.4,"s":[784.068,5.309],"i":{"x":[0,1],"y":[1,1]},"o":{"x":[0.5,0],"y":[0,0]}},{"t":35.4,"s":[476.068,5.309],"i":{"x":[1,1],"y":[1,1]},"o":{"x":[0,0],"y":[0,0]}},{"t":67.2,"s":[476.068,5.309],"h":1}]}},"w":219,"h":87,"ip":0,"op":68.2,"st":0,"refId":"39"},{"ind":105,"ty":0,"parent":1,"ks":{"a":{"a":0,"k":[2,2]},"o":{"a":1,"k":[{"t":0,"s":[100],"i":{"x":1,"y":1},"o":{"x":0,"y":0}},{"t":12,"s":[0],"h":1},{"t":67.2,"s":[0],"h":1}]},"p":{"a":1,"k":[{"t":0,"s":[89.144,6.015],"i":{"x":[0,1],"y":[1,1]},"o":{"x":[0.5,0],"y":[0,0]}},{"t":30,"s":[-555.856,6.015],"i":{"x":[1,1],"y":[1,1]},"o":{"x":[0,0],"y":[0,0]}},{"t":67.2,"s":[-555.856,6.015],"h":1}]}},"w":592,"h":109,"ip":0,"op":68.2,"st":0,"refId":"103"},{"ind":112,"ty":0,"parent":108,"ks":{},"w":25,"h":28,"ip":0,"op":68.2,"st":0,"refId":"110"},{"ind":108,"ty":3,"parent":107,"ks":{"s":{"a":0,"k":[219.91,219.6]}},"ip":0,"op":68.2,"st":0},{"ind":107,"ty":3,"parent":106,"ks":{"p":{"a":0,"k":[0,0]}},"ip":0,"op":68.2,"st":0},{"ind":118,"ty":0,"parent":114,"ks":{},"w":28,"h":28,"ip":0,"op":68.2,"st":0,"refId":"116"},{"ind":114,"ty":3,"parent":113,"ks":{"s":{"a":0,"k":[219.91,219.6]}},"ip":0,"op":68.2,"st":0},{"ind":113,"ty":3,"parent":106,"ks":{"p":{"a":0,"k":[59.376,0]}},"ip":0,"op":68.2,"st":0},{"ind":124,"ty":0,"parent":120,"ks":{},"w":7,"h":7,"ip":0,"op":68.2,"st":0,"refId":"122"},{"ind":120,"ty":3,"parent":119,"ks":{"s":{"a":0,"k":[219.91,219.6]}},"ip":0,"op":68.2,"st":0},{"ind":119,"ty":3,"parent":106,"ks":{"p":{"a":0,"k":[131.948,46.116]}},"ip":0,"op":68.2,"st":0},{"ind":106,"ty":3,"parent":1,"ks":{"p":{"a":1,"k":[{"t":0,"s":[1024.394,29.156],"i":{"x":[1,1],"y":[1,1]},"o":{"x":[0,0],"y":[0,0]}},{"t":10.2,"s":[1024.394,29.156],"i":{"x":[0,1],"y":[1,1]},"o":{"x":[0.5,0],"y":[0,0]}},{"t":58.2,"s":[158.394,29.156],"i":{"x":[1,1],"y":[1,1]},"o":{"x":[0,0],"y":[0,0]}},{"t":67.2,"s":[158.394,29.156],"h":1}]}},"ip":0,"op":68.2,"st":0},{"ind":1,"ty":3,"parent":0,"ks":{},"ip":0,"op":68.2,"st":0},{"ind":125,"ty":4,"parent":0,"ks":{},"ip":0,"op":68.2,"st":0,"shapes":[{"ty":"rc","p":{"a":0,"k":[592.5,60.5]},"r":{"a":0,"k":0},"s":{"a":0,"k":[1185,121]}},{"ty":"fl","c":{"a":0,"k":[1,1,1,0]},"o":{"a":0,"k":0}}]},{"ind":0,"ty":3,"ks":{},"ip":0,"op":68.2,"st":0}],"meta":{"g":"https://jitter.video"},"op":67.2,"v":"5.7.4","w":1185}